tk_async_execute/__init__.py
tk_async_execute/doc.py
tk_async_execute/utils.py
tk_async_execute/widget.py
tkinter_async_execute-1.4.0.dist-info/LICENSE
tkinter_async_execute-1.4.0.dist-info/METADATA
tkinter_async_execute-1.4.0.dist-info/WHEEL
tkinter_async_execute-1.4.0.dist-info/top_level.txt
tkinter_async_execute-1.4.0.dist-info/RECORD
