Metadata-Version: 2.2
Name: tkinter-async-execute
Version: 1.4.0
Summary: Simple library that allows interaction between Tkinter and asyncio event loop running in a seperate thread.
Author: David Hozic
Keywords: Tkinter,asyncio,Async execute,Execution progress window,Thread-safe
Classifier: Programming Language :: Python :: 3
Classifier: License :: OSI Approved :: MIT License
Classifier: Operating System :: OS Independent
Requires-Python: >=3.8
License-File: LICENSE
Provides-Extra: dev
Requires-Dist: sphinx==7.1.2; extra == "dev"
Requires-Dist: sphinx-autobuild==2021.3.14; extra == "dev"
Requires-Dist: sphinx-copybutton==0.5.2; extra == "dev"
Requires-Dist: furo==2023.8.17; extra == "dev"
Requires-Dist: enum-tools[sphinx]==0.10.0; extra == "dev"
Requires-Dist: sphinx-design[furo]==0.5.0; extra == "dev"
Requires-Dist: readthedocs-sphinx-search==0.3.1; extra == "dev"
Requires-Dist: sphinxcontrib-svg2pdfconverter==1.2.2; extra == "dev"
